jacobi_vision/__init__.py
jacobi_vision/color.py
jacobi_vision/image.py
jacobi_vision/calibration/__init__.py
jacobi_vision/calibration/analyze.py
jacobi_vision/calibration/ball.py
jacobi_vision/calibration/main.py
jacobi_vision/calibration/record.py
jacobi_vision/drivers/__init__.py
jacobi_vision/drivers/simulated_camera_driver.py
jacobi_vision/drivers/virtual_camera_driver.py
jacobi_vision-0.4.4.dist-info/licenses/LICENSE
jacobi_vision-0.4.4.dist-info/METADATA
jacobi_vision-0.4.4.dist-info/WHEEL
jacobi_vision-0.4.4.dist-info/entry_points.txt
jacobi_vision-0.4.4.dist-info/top_level.txt
jacobi_vision-0.4.4.dist-info/RECORD
