Metadata-Version: 2.4
Name: jacobi-vision
Version: 0.4.4
Summary: Next-Generation Computer Vision for Robots.
Author-email: Lars Berscheid <lars.berscheid@jacobirobotics.com>, Andreas ten Pas <andreas.tenpas@jacobirobotics.com>
License: Copyright (c) 2024 Jacobi Robotics Inc.
Project-URL: homepage, https://www.jacobirobotics.com
Project-URL: documentation, https://docs.jacobirobotics.com
Keywords: robotics,computer-vision
Classifier: Development Status :: 4 - Beta
Classifier: Intended Audience :: Science/Research
Classifier: Topic :: Scientific/Engineering
Classifier: License :: Other/Proprietary License
Classifier: Programming Language :: Python
Requires-Python: >=3.10
License-File: LICENSE
Requires-Dist: numpy>=2.1
Requires-Dist: opencv-python>=4.10
Requires-Dist: opencv-contrib-python>=4.10
Requires-Dist: scipy>=1.14
Dynamic: license-file
